{
  "data": [
    {
      "id": "1000",
      "code": "f230fh0g3",
      "name": "Bamboo Watch",
      "description": "Детальное описание для часов. Внутри будет 2 фотографии.",
      "image": ["bamboo-watch.jpg", "bamboo-watch2.jpg"],
      "price": 65,
      "category": "Аксессуары",
      "quantity": 24,
      "inventoryStatus": "INSTOCK",
      "rating": 5,
      "feedbacksCount": 210,
      "count": 0
    },
    {
      "id": "1001",
      "code": "nvklal433",
      "name": "Black Watch",
      "description": "Другие часы. Детальное описание. Часы со стрелками, без цифр.",
      "image": ["black-watch.jpg"],
      "price": 72,
      "category": "Аксессуары",
      "quantity": 61,
      "inventoryStatus": "INSTOCK",
      "rating": 4,
      "count": 0
    },
    {
      "id": "1002",
      "code": "zz21cz3c1",
      "name": "Blue Band",
      "description": "Детальное описание продукта. У каждого разное.",
      "image": ["blue-band.jpg"],
      "price": 79,
      "category": "Фитнес и спорт",
      "quantity": 2,
      "inventoryStatus": "LOWSTOCK",
      "rating": 3,
      "count": 0
    },
    {
      "id": "1003",
      "code": "244wgerg2",
      "name": "Blue T-Shirt",
      "description": "Футболка синего цвета. ",
      "image": ["blue-t-shirt.jpg"],
      "price": 29,
      "category": "Одежда",
      "quantity": 25,
      "inventoryStatus": "INSTOCK",
      "rating": 5,
      "count": 0
    },
    {
      "id": "1004",
      "code": "h456wer53",
      "name": "Bracelet",
      "description": "Детальное описание продукта. У каждого разное.",
      "image": ["bracelet.jpg"],
      "price": 15,
      "category": "Аксессуары",
      "quantity": 73,
      "inventoryStatus": "INSTOCK",
      "rating": 4,
      "count": 0
    },
    {
      "id": "1005",
      "code": "av2231fwg",
      "name": "Brown Purse",
      "description": "Сумка для хранения и переноса личных вещей. Есть только в коричневом цвете.",
      "image": ["brown-purse.jpg"],
      "price": 120,
      "category": "Аксессуары",
      "quantity": 0,
      "inventoryStatus": "OUTOFSTOCK",
      "rating": 4,
      "count": 0
    },
    {
      "id": "1006",
      "code": "bib36pfvm",
      "name": "Chakra Bracelet",
      "description": "Детальное описание продукта. У каждого разное.",
      "image": ["chakra-bracelet.jpg"],
      "price": 32,
      "category": "Аксессуары",
      "quantity": 5,
      "inventoryStatus": "LOWSTOCK",
      "rating": 3,
      "count": 0
    },
    {
      "id": "1007",
      "code": "mbvjkgip5",
      "name": "Galaxy Earrings",
      "description": "Детальное описание продукта. У каждого разное.",
      "image": ["galaxy-earrings.jpg"],
      "price": 34,
      "category": "Аксессуары",
      "quantity": 23,
      "inventoryStatus": "INSTOCK",
      "rating": 5,
      "count": 0
    },
    {
      "id": "1008",
      "code": "vbb124btr",
      "name": "Game Controller",
      "description": "Детальное описание продукта. У каждого разное.",
      "image": ["game-controller.jpg"],
      "price": 99,
      "category": "Электроника",
      "quantity": 2,
      "inventoryStatus": "LOWSTOCK",
      "rating": 4,
      "count": 0
    },
    {
      "id": "1009",
      "code": "cm230f032",
      "name": "Gaming Set",
      "description": "Детальное описание продукта. У каждого разное.",
      "image": ["gaming-set.jpg"],
      "price": 299,
      "category": "Электроника",
      "quantity": 63,
      "inventoryStatus": "INSTOCK",
      "rating": 3,
      "count": 0
    },
    {
      "id": "1010",
      "code": "plb34234v",
      "name": "Gold Phone Case",
      "description": "Детальное описание продукта. У каждого разное.",
      "image": ["gold-phone-case.jpg"],
      "price": 24,
      "category": "Аксессуары",
      "quantity": 0,
      "inventoryStatus": "OUTOFSTOCK",
      "rating": 4,
      "count": 0
    },
    {
      "id": "1011",
      "code": "4920nnc2d",
      "name": "Green Earbuds",
      "description": "Детальное описание продукта. У каждого разное.",
      "image": ["green-earbuds.jpg"],
      "price": 89,
      "category": "Электроника",
      "quantity": 23,
      "inventoryStatus": "INSTOCK",
      "rating": 4,
      "count": 0
    },
    {
      "id": "1012",
      "code": "250vm23cc",
      "name": "Green T-Shirt",
      "description": "Детальное описание продукта. У каждого разное.",
      "image": ["green-t-shirt.jpg"],
      "price": 49,
      "category": "Одежда",
      "quantity": 74,
      "inventoryStatus": "INSTOCK",
      "rating": 5,
      "count": 0
    },
    {
      "id": "1013",
      "code": "fldsmn31b",
      "name": "Grey T-Shirt",
      "description": "Детальное описание продукта. У каждого разное.",
      "image": ["grey-t-shirt.jpg"],
      "price": 48,
      "category": "Одежда",
      "quantity": 0,
      "inventoryStatus": "OUTOFSTOCK",
      "rating": 3,
      "count": 0
    },
    {
      "id": "1014",
      "code": "waas1x2as",
      "name": "Headphones",
      "description": "Детальное описание продукта. У каждого разное.",
      "image": ["headphones.jpg"],
      "price": 175,
      "category": "Электроника",
      "quantity": 8,
      "inventoryStatus": "LOWSTOCK",
      "rating": 5,
      "count": 0
    },
    {
      "id": "1015",
      "code": "vb34btbg5",
      "name": "Light Green T-Shirt",
      "description": "Детальное описание продукта. У каждого разное.",
      "image": ["light-green-t-shirt.jpg"],
      "price": 49,
      "category": "Одежда",
      "quantity": 34,
      "inventoryStatus": "INSTOCK",
      "rating": 4,
      "count": 0
    },
    {
      "id": "1016",
      "code": "k8l6j58jl",
      "name": "Lime Band",
      "description": "Детальное описание продукта. У каждого разное.",
      "image": ["lime-band.jpg"],
      "price": 79,
      "category": "Фитнес и спорт",
      "quantity": 12,
      "inventoryStatus": "INSTOCK",
      "rating": 3,
      "count": 0
    },
    {
      "id": "1017",
      "code": "v435nn85n",
      "name": "Mini Speakers",
      "description": "Детальное описание продукта. У каждого разное.",
      "image": ["mini-speakers.jpg"],
      "price": 85,
      "category": "Одежда",
      "quantity": 42,
      "inventoryStatus": "INSTOCK",
      "rating": 4,
      "count": 0
    },
    {
      "id": "1018",
      "code": "09zx9c0zc",
      "name": "Painted Phone Case",
      "description": "Детальное описание продукта. У каждого разное.",
      "image": ["painted-phone-case.jpg"],
      "price": 56,
      "category": "Аксессуары",
      "quantity": 41,
      "inventoryStatus": "INSTOCK",
      "rating": 5,
      "count": 0
    },
    {
      "id": "1019",
      "code": "mnb5mb2m5",
      "name": "Pink Band",
      "description": "Детальное описание продукта. У каждого разное.",
      "image": ["pink-band.jpg"],
      "price": 79,
      "category": "Фитнес и спорт",
      "quantity": 63,
      "inventoryStatus": "INSTOCK",
      "rating": 4,
      "count": 0
    },
    {
      "id": "1020",
      "code": "r23fwf2w3",
      "name": "Pink Purse",
      "description": "Детальное описание продукта. У каждого разное.",
      "image": ["pink-purse.jpg"],
      "price": 110,
      "category": "Аксессуары",
      "quantity": 0,
      "inventoryStatus": "OUTOFSTOCK",
      "rating": 4,
      "count": 0
    },
    {
      "id": "1021",
      "code": "pxpzczo23",
      "name": "Purple Band",
      "description": "Детальное описание продукта. У каждого разное.",
      "image": ["purple-band.jpg"],
      "price": 79,
      "category": "Фитнес и спорт",
      "quantity": 6,
      "inventoryStatus": "LOWSTOCK",
      "rating": 3,
      "count": 0
    },
    {
      "id": "1022",
      "code": "2c42cb5cb",
      "name": "Purple Gemstone Necklace",
      "description": "Детальное описание продукта. У каждого разное.",
      "image": ["purple-gemstone-necklace.jpg"],
      "price": 45,
      "category": "Аксессуары",
      "quantity": 62,
      "inventoryStatus": "INSTOCK",
      "rating": 4,
      "count": 0
    },
    {
      "id": "1023",
      "code": "5k43kkk23",
      "name": "Purple T-Shirt",
      "description": "Детальное описание продукта. У каждого разное.",
      "image": ["purple-t-shirt.jpg"],
      "price": 49,
      "category": "Одежда",
      "quantity": 2,
      "inventoryStatus": "LOWSTOCK",
      "rating": 5,
      "count": 0
    },
    {
      "id": "1024",
      "code": "lm2tny2k4",
      "name": "Shoes",
      "description": "Детальное описание продукта. У каждого разное.",
      "image": ["shoes.jpg"],
      "price": 64,
      "category": "Одежда",
      "quantity": 0,
      "inventoryStatus": "INSTOCK",
      "rating": 4,
      "count": 0
    },
    {
      "id": "1025",
      "code": "nbm5mv45n",
      "name": "Sneakers",
      "description": "Детальное описание продукта. У каждого разное.",
      "image": ["sneakers.jpg"],
      "price": 78,
      "category": "Одежда",
      "quantity": 52,
      "inventoryStatus": "INSTOCK",
      "rating": 4,
      "count": 0
    },
    {
      "id": "1026",
      "code": "zx23zc42c",
      "name": "Teal T-Shirt",
      "description": "Детальное описание продукта. У каждого разное.",
      "image": ["teal-t-shirt.jpg"],
      "price": 49,
      "category": "Одежда",
      "quantity": 3,
      "inventoryStatus": "LOWSTOCK",
      "rating": 3,
      "count": 0
    },
    {
      "id": "1027",
      "code": "acvx872gc",
      "name": "Yellow Earbuds",
      "description": "Детальное описание продукта. У каждого разное.",
      "image": ["yellow-earbuds.jpg"],
      "price": 89,
      "category": "Электроника",
      "quantity": 35,
      "inventoryStatus": "INSTOCK",
      "rating": 3,
      "count": 0
    },
    {
      "id": "1028",
      "code": "tx125ck42",
      "name": "Yoga Mat",
      "description": "Детальное описание продукта. У каждого разное.",
      "image": ["yoga-mat.jpg"],
      "price": 20,
      "category": "Фитнес и спорт",
      "quantity": 15,
      "inventoryStatus": "INSTOCK",
      "rating": 5,
      "count": 0
    },
    {
      "id": "1029",
      "code": "gwuby345v",
      "name": "Yoga Set",
      "description": "Детальное описание продукта. У каждого разное.",
      "image": ["yoga-set.jpg"],
      "price": 20,
      "category": "Фитнес и спорт",
      "quantity": 25,
      "inventoryStatus": "INSTOCK",
      "rating": 5,
      "count": 0
    }
  ]
}
